COPYING.txt
README.txt
setup.py
svnrepo.py
svnrepo_test.py
svnrepo.egg-info/PKG-INFO
svnrepo.egg-info/SOURCES.txt
svnrepo.egg-info/dependency_links.txt
svnrepo.egg-info/top_level.txt
