Metadata-Version: 1.0
Name: svnrepo
Version: 0.1
Summary: A pythonic API to a local subversion repository.
Home-page: http://www.rufuspollock.org/code/svnrepo/
Author: Rufus Pollock (Open Knowledge Foundation)
Author-email: rufus@rufuspollock.org
License: MIT
Download-URL: http://www.rufuspollock.org/code/svnrepo/svnrepo.py
Keywords: svn subversion python api
Platform: UNKNOWN
Classifier: Development Status :: 3 - Alpha
Classifier: Environment :: Console
Classifier: Intended Audience :: Developers
Classifier: License :: OSI Approved :: MIT License
Classifier: Operating System :: OS Independent
Classifier: Programming Language :: Python
Classifier: Topic :: Software Development :: Libraries :: Python Modules
